perceptrain/__init__.py
perceptrain/config.py
perceptrain/data.py
perceptrain/log_config.yaml
perceptrain/models.py
perceptrain/optimize_step.py
perceptrain/parameters.py
perceptrain/stages.py
perceptrain/tensors.py
perceptrain/trainer.py
perceptrain/types.py
perceptrain/callbacks/__init__.py
perceptrain/callbacks/callback.py
perceptrain/callbacks/callbackmanager.py
perceptrain/callbacks/saveload.py
perceptrain/callbacks/writer_registry.py
perceptrain/information/__init__.py
perceptrain/information/information_content.py
perceptrain/loss/__init__.py
perceptrain/loss/loss.py
perceptrain/optimizers/__init__.py
perceptrain/optimizers/adam_lbfgs.py
perceptrain/train_utils/__init__.py
perceptrain/train_utils/accelerator.py
perceptrain/train_utils/base_trainer.py
perceptrain/train_utils/config_manager.py
perceptrain/train_utils/distribution.py
perceptrain/train_utils/execution.py
perceptrain-0.1.0.dist-info/METADATA
perceptrain-0.1.0.dist-info/WHEEL
perceptrain-0.1.0.dist-info/licenses/LICENSE
perceptrain-0.1.0.dist-info/RECORD
