Metadata-Version: 2.4
Name: perceptrain
Version: 0.1.0
Summary: Pasqal interface for training machine learning models.
Author-email: Manu Lahariya <manu.lahariya@pasqal.com>, Daniele Cucurachi <daniele.cucurachi@pasqal.com>, Ignacio Fernández Graña <ignacio.fernandez-grana@pasqal.com>, Giorgio Tosti Balducci <giorgio.tosti-balducci@pasqal.com>
License: Apache 2.0
License-File: LICENSE
Classifier: License :: OSI Approved :: Apache Software License
Classifier: Programming Language :: Python
Classifier: Programming Language :: Python :: 3
Classifier: Programming Language :: Python :: 3.9
Classifier: Programming Language :: Python :: 3.10
Classifier: Programming Language :: Python :: 3.11
Classifier: Programming Language :: Python :: 3.12
Classifier: Programming Language :: Python :: Implementation :: CPython
Classifier: Programming Language :: Python :: Implementation :: PyPy
Requires-Python: >=3.9
Requires-Dist: livelossplot
Requires-Dist: matplotlib
Requires-Dist: nevergrad
Requires-Dist: numpy
Requires-Dist: pyqtorch==1.7.5
Requires-Dist: pyyaml
Requires-Dist: rich
Requires-Dist: tensorboard>=2.12.0
Requires-Dist: torch
Provides-Extra: all
Requires-Dist: dlprof; extra == 'all'
Requires-Dist: mlflow; extra == 'all'
Provides-Extra: dlprof
Requires-Dist: nvidia-dlprof[pytorch]; extra == 'dlprof'
Requires-Dist: nvidia-pyindex; extra == 'dlprof'
Provides-Extra: mlflow
Requires-Dist: mlflow; extra == 'mlflow'
